webnull.py
webnull-1.0.1.dist-info/DESCRIPTION.rst
webnull-1.0.1.dist-info/METADATA
webnull-1.0.1.dist-info/RECORD
webnull-1.0.1.dist-info/WHEEL
webnull-1.0.1.dist-info/entry_points.txt
webnull-1.0.1.dist-info/metadata.json
webnull-1.0.1.dist-info/top_level.txt
