Metadata-Version: 2.0
Name: webnull
Version: 1.0.1
Summary: A tool for putting hosts into a blackhole
Home-page: https://github.com/macrael/webnull
Author: MacRae Linton
Author-email: macrae@macrael.com
License: BSD
Keywords: distractions productivity
Platform: UNKNOWN
Classifier: Environment :: MacOS X
Classifier: Operating System :: MacOS :: MacOS X
Classifier: Intended Audience :: End Users/Desktop
Classifier: License :: OSI Approved :: BSD License
Classifier: Programming Language :: Python :: 2.7
Provides-Extra: test
Requires-Dist: watchdog; extra == 'test'
